{"VpIXRwCzDMuTL8+qupseTw==":"microsoft-graph-96x47.png","AzlZXIg/kfs0SsWxBGeU+w==":"mbr-196x196.png","tArR/0E4r6kitQ0CYvRM1Q==":"mbr-1920x1280.jpg","u/BluH/lKhCIWotiRISqlQ==":"mbr-1920x1275.jpg","6BrPEIRuFfkGDYVFZxfpCg==":"mbr-1-1920x1280.jpg","NC2gcct94kNZm7lSIP4wbg==":"mbr-1920x1080.png","KNCSQqiiJRRiEr22N1qGhQ==":"mbr-1920x1141.jpg","k2TRJAm9Ma3RBNX9HzyXtQ==":"mbr-2-1920x1280.jpg","4TRQ7X5NOSF6apyOWDyOOA==":"mbr-1280x1920.png","H3Ez8jZM1Y0Mwu/gMd1elA==":"mbr-1920x1281.jpg","YMjfq5FXBz2Y1fxQNGdd6g==":"mbr-1620x1080.jpg","bsu+MOenxTAlwo0WcDkwpw==":"mbr-1920x1455.jpg","SM/mY/q14fJIQRx85t24uQ==":"mbr-1920x1774.jpg","Qu73YGF6J506Y5axJBr5qw==":"mbr-1920x1441.jpg","PLNxzeiXKQm+ShM+7ktUZw==":"authorization%20code%20flow.svg","5wnx04MYT1WOHirfcafrBg==":"client%20credentials%20flow.svg"}